devdeck/__init__.py
devdeck/deck_context.py
devdeck/deck_manager.py
devdeck/filters.py
devdeck/main.py
devdeck/assets/font-awesome/licence.txt
devdeck/assets/font-awesome/microphone-mute.png
devdeck/assets/font-awesome/microphone.png
devdeck/assets/font-awesome/stopwatch.png
devdeck/assets/font-awesome/users.png
devdeck/assets/font-awesome/volume-off-solid.png
devdeck/assets/font-awesome/volume-up-solid.png
devdeck/controls/__init__.py
devdeck/controls/clock_control.py
devdeck/controls/command_control.py
devdeck/controls/mic_mute_control.py
devdeck/controls/name_list_control.py
devdeck/controls/timer_control.py
devdeck/controls/volume_level_control.py
devdeck/controls/volume_mute_control.py
devdeck/decks/__init__.py
devdeck/decks/single_page_deck_controller.py
devdeck/decks/volume_deck.py
devdeck/settings/__init__.py
devdeck/settings/control_settings.py
devdeck/settings/deck_settings.py
devdeck/settings/devdeck_settings.py
devdeck/settings/validation_error.py
tests/__init__.py
tests/testing_utils.py
tests/devdeck/__init__.py
tests/devdeck/test_deck_manager.py
tests/devdeck/controls/__init__.py
tests/devdeck/controls/test_command_control.py
tests/devdeck/controls/test_name_list_control.py
tests/devdeck/controls/test_timer_control.py
tests/devdeck/settings/__init__.py
tests/devdeck/settings/test_control_setting.py
tests/devdeck/settings/test_devdeck_settings.py
tests/devdeck/settings/test_validation_error.py
devdeck-1.0.13.dist-info/METADATA
devdeck-1.0.13.dist-info/WHEEL
devdeck-1.0.13.dist-info/entry_points.txt
devdeck-1.0.13.dist-info/top_level.txt
devdeck-1.0.13.dist-info/RECORD
