Metadata-Version: 2.1
Name: devdeck
Version: 1.0.13
Summary: A developer's approach to using a Stream Deck.
Home-page: https://github.com/jamesridgway/devdeck
Author: James Ridgway
Author-email: UNKNOWN
License: MIT
Platform: UNKNOWN
Requires-Dist: assertpy
Requires-Dist: cerberus
Requires-Dist: devdeck-core (==1.0.7)
Requires-Dist: emoji
Requires-Dist: jsonschema
Requires-Dist: pillow
Requires-Dist: pulsectl
Requires-Dist: pytest
Requires-Dist: pyyaml
Requires-Dist: requests
Requires-Dist: streamdeck
